deepdiff/__init__.py
deepdiff/anyset.py
deepdiff/base.py
deepdiff/commands.py
deepdiff/deephash.py
deepdiff/delta.py
deepdiff/diff.py
deepdiff/distance.py
deepdiff/helper.py
deepdiff/lfucache.py
deepdiff/model.py
deepdiff/operator.py
deepdiff/path.py
deepdiff/py.typed
deepdiff/search.py
deepdiff/serialization.py
deepdiff/summarize.py
deepdiff-8.4.1.dist-info/AUTHORS.md
deepdiff-8.4.1.dist-info/LICENSE
deepdiff-8.4.1.dist-info/METADATA
deepdiff-8.4.1.dist-info/WHEEL
deepdiff-8.4.1.dist-info/entry_points.txt
deepdiff-8.4.1.dist-info/top_level.txt
deepdiff-8.4.1.dist-info/zip-safe
deepdiff-8.4.1.dist-info/RECORD
