Metadata-Version: 2.2
Name: deepdiff
Version: 8.4.1
Summary: Deep Difference and Search of any Python object/data. Recreate objects by adding adding deltas to each other.
Home-page: https://github.com/seperman/deepdiff
Download-URL: https://github.com/seperman/deepdiff/tarball/master
Author: Seperman
Author-email: sep@zepworks.com
License: MIT
Classifier: Intended Audience :: Developers
Classifier: Operating System :: OS Independent
Classifier: Topic :: Software Development
Classifier: Programming Language :: Python :: 3.8
Classifier: Programming Language :: Python :: 3.9
Classifier: Programming Language :: Python :: 3.10
Classifier: Programming Language :: Python :: 3.11
Classifier: Programming Language :: Python :: 3.12
Classifier: Programming Language :: Python :: 3.13
Classifier: Programming Language :: Python :: Implementation :: PyPy
Classifier: Development Status :: 5 - Production/Stable
Classifier: License :: OSI Approved :: MIT License
Requires-Python: >=3.8
License-File: LICENSE
License-File: AUTHORS.md
Requires-Dist: orderly-set<6,>=5.3.0
Provides-Extra: cli
Requires-Dist: click==8.1.8; extra == "cli"
Requires-Dist: pyyaml==6.0.2; extra == "cli"
Provides-Extra: optimize
Requires-Dist: orjson; extra == "optimize"
Dynamic: author
Dynamic: author-email
Dynamic: classifier
Dynamic: description
Dynamic: description-content-type
Dynamic: download-url
Dynamic: home-page
Dynamic: license
Dynamic: provides-extra
Dynamic: requires-dist
Dynamic: requires-python
Dynamic: summary
